simpledt/__init__.py
simpledt/simpledatatable.py
simpledatatable-0.3.4.dist-info/LICENSE
simpledatatable-0.3.4.dist-info/METADATA
simpledatatable-0.3.4.dist-info/WHEEL
simpledatatable-0.3.4.dist-info/top_level.txt
simpledatatable-0.3.4.dist-info/RECORD
